[
    {
        "message_id": "1f8bc413-5376-4e54-931a-fee15fad5a79",
        "type": "statistics",
        "current_viewers": 112,
        "total_viewers": "1.4万",
        "timestamp": "2025-03-25 02:04:21"
    },
    {
        "message_id": "7f972dd4-64e2-4b1f-ad7f-0a4ae9675d1e",
        "type": "statistics",
        "current_viewers": 114,
        "total_viewers": "1.4万",
        "timestamp": "2025-03-25 02:04:22"
    },
    {
        "message_id": "ea132baf-0875-415c-9b4a-b324aa9a8676",
        "type": "statistics",
        "current_viewers": 119,
        "total_viewers": "1.4万",
        "timestamp": "2025-03-25 02:04:23"
    },
    {
        "message_id": "69c5d694-8ec5-4b39-b8ba-96efd5d861b6",
        "type": "statistics",
        "current_viewers": 117,
        "total_viewers": "1.4万",
        "timestamp": "2025-03-25 02:04:32"
    },
    {
        "message_id": "40b78c58-7ac8-4a05-8bea-cf661836e145",
        "type": "statistics",
        "current_viewers": 110,
        "total_viewers": "1.4万",
        "timestamp": "2025-03-25 02:04:38"
    },
    {
        "message_id": "f2fba56e-5830-4c9f-95b2-8160c1d50a9f",
        "type": "statistics",
        "current_viewers": 106,
        "total_viewers": "1.4万",
        "timestamp": "2025-03-25 02:04:46"
    }
]